odoo8_addon_base_gs1_barcode-8.0.1.1.0-py2.7-nspkg.pth
odoo_addons/base_gs1_barcode/__openerp__.py
odoo_addons/base_gs1_barcode/__init__.py
odoo_addons/base_gs1_barcode/README.rst
odoo_addons/base_gs1_barcode/security/ir.model.access.csv
odoo_addons/base_gs1_barcode/models/__init__.py
odoo_addons/base_gs1_barcode/models/gs1_barcode.py
odoo_addons/base_gs1_barcode/models/res_users.py
odoo_addons/base_gs1_barcode/i18n/pt.po
odoo_addons/base_gs1_barcode/i18n/it.po
odoo_addons/base_gs1_barcode/i18n/es.po
odoo_addons/base_gs1_barcode/i18n/tr.po
odoo_addons/base_gs1_barcode/i18n/gl.po
odoo_addons/base_gs1_barcode/i18n/ca.po
odoo_addons/base_gs1_barcode/i18n/sl.po
odoo_addons/base_gs1_barcode/i18n/es_ES.po
odoo_addons/base_gs1_barcode/i18n/pt_PT.po
odoo_addons/base_gs1_barcode/i18n/nl.po
odoo_addons/base_gs1_barcode/i18n/am.po
odoo_addons/base_gs1_barcode/i18n/de.po
odoo_addons/base_gs1_barcode/i18n/base_gs1_barcode.pot
odoo_addons/base_gs1_barcode/i18n/fr.po
odoo_addons/base_gs1_barcode/i18n/pt_BR.po
odoo_addons/base_gs1_barcode/i18n/el_GR.po
odoo_addons/base_gs1_barcode/i18n/fi.po
odoo_addons/base_gs1_barcode/test/gs1_barcode_test.yml
odoo_addons/base_gs1_barcode/views/gs1_barcode.xml
odoo_addons/base_gs1_barcode/views/res_users.xml
odoo_addons/base_gs1_barcode/data/gs1_barcode.csv
odoo_addons/base_gs1_barcode/static/description/icon.png
odoo8_addon_base_gs1_barcode-8.0.1.1.0.dist-info/top_level.txt
odoo8_addon_base_gs1_barcode-8.0.1.1.0.dist-info/WHEEL
odoo8_addon_base_gs1_barcode-8.0.1.1.0.dist-info/RECORD
odoo8_addon_base_gs1_barcode-8.0.1.1.0.dist-info/metadata.json
odoo8_addon_base_gs1_barcode-8.0.1.1.0.dist-info/DESCRIPTION.rst
odoo8_addon_base_gs1_barcode-8.0.1.1.0.dist-info/METADATA
odoo8_addon_base_gs1_barcode-8.0.1.1.0.dist-info/namespace_packages.txt
