Metadata-Version: 2.0
Name: odoo8-addon-base-gs1-barcode
Version: 8.0.1.1.0
Summary: Decoding API for GS1-128 (aka UCC/EAN-128) and GS1-Datamatrix
Home-page: http://numerigraphe.com
Author: UNKNOWN
Author-email: UNKNOWN
License: AGPL-3
Platform: UNKNOWN
Requires-Dist: odoo (<9.0a,>=8.0a)
Classifier: Programming Language :: Python :: 2.7
Classifier: Framework :: Odoo
Classifier: License :: OSI Approved :: GNU Affero General Public License v3
